CHANGELOG.rst
LICENSE.txt
MANIFEST.in
README.rst
requirements.txt
setup.py
src/zeo_connector/__init__.py
src/zeo_connector/transaction_manager.py
src/zeo_connector/zeo_conf_wrapper.py
src/zeo_connector/zeo_wrapper.py
src/zeo_connector/zeo_wrapper_prototype.py
src/zeo_connector.egg-info/PKG-INFO
src/zeo_connector.egg-info/SOURCES.txt
src/zeo_connector.egg-info/dependency_links.txt
src/zeo_connector.egg-info/not-zip-safe
src/zeo_connector.egg-info/requires.txt
src/zeo_connector.egg-info/top_level.txt
src/zeo_connector/examples/__init__.py
src/zeo_connector/examples/database_handler.py