Metadata-Version: 1.1
Name: zeo-connector
Version: 0.4.8
Summary: Wrappers, which make working with ZEO little bit nicer.
Home-page: https://github.com/Bystroushaak/zeo_connector
Author: Bystroushaak
Author-email: bystrousak@kitakitsune.org
License: MIT
Platform: UNKNOWN
Classifier: Development Status :: 4 - Beta
Classifier: Intended Audience :: Developers
Classifier: Programming Language :: Python :: 2
Classifier: Programming Language :: Python :: 2.7
Classifier: License :: OSI Approved :: MIT License
